{
    "tortoises": [
        {
            "id": 0,
            "top": 848008,
            "position": 136819979
        },
        {
            "id": 1,
            "top": 848008,
            "position": 116782816
        },
        {
            "id": 2,
            "top": 848008,
            "position": 151329387
        },
        {
            "id": 3,
            "top": 848008,
            "position": 207899299
        },
        {
            "id": 4,
            "top": 848008,
            "position": 175174772
        },
        {
            "id": 5,
            "top": 848008,
            "position": 110121284
        },
        {
            "id": 6,
            "top": 848008,
            "position": 172543562
        },
        {
            "id": 7,
            "top": 848008,
            "position": 222726838
        },
        {
            "id": 8,
            "top": 848008,
            "position": 326483080
        },
        {
            "id": 9,
            "top": 848008,
            "position": 199923543
        },
        {
            "id": 10,
            "top": 848008,
            "position": 74624704
        },
        {
            "id": 11,
            "top": 848008,
            "position": 179220657
        },
        {
            "id": 12,
            "top": 848008,
            "position": 112361368
        },
        {
            "id": 13,
            "top": 848008,
            "position": 298498816
        },
        {
            "id": 14,
            "top": 848008,
            "position": 137801031
        },
        {
            "id": 15,
            "top": 848008,
            "position": 169394760
        },
        {
            "id": 16,
            "top": 848008,
            "position": 122274377
        },
        {
            "id": 17,
            "top": 848008,
            "position": 169178744
        },
        {
            "id": 18,
            "top": 848008,
            "position": 142431838
        },
        {
            "id": 19,
            "top": 848008,
            "position": 130738587
        },
        {
            "id": 20,
            "top": 848008,
            "position": 180367654
        },
        {
            "id": 21,
            "top": 848008,
            "position": 162355952
        },
        {
            "id": 22,
            "top": 848008,
            "position": 159850344
        },
        {
            "id": 23,
            "top": 848008,
            "position": 51304520
        },
        {
            "id": 24,
            "top": 848008,
            "position": 98719677
        },
        {
            "id": 25,
            "top": 848008,
            "position": 179356396
        },
        {
            "id": 26,
            "top": 848008,
            "position": 142460663
        },
        {
            "id": 27,
            "top": 848008,
            "position": 167021889
        },
        {
            "id": 28,
            "top": 848008,
            "position": 142516791
        },
        {
            "id": 29,
            "top": 848008,
            "position": 151833951
        },
        {
            "id": 30,
            "top": 848008,
            "position": 37312216
        },
        {
            "id": 31,
            "top": 848008,
            "position": 81628698
        },
        {
            "id": 32,
            "top": 848008,
            "position": 142549954
        },
        {
            "id": 33,
            "top": 848008,
            "position": 53828289
        },
        {
            "id": 34,
            "top": 848008,
            "position": 104304984
        },
        {
            "id": 35,
            "top": 848008,
            "position": 166594096
        },
        {
            "id": 36,
            "top": 848008,
            "position": 244768044
        },
        {
            "id": 37,
            "top": 848008,
            "position": 161951599
        },
        {
            "id": 38,
            "top": 848008,
            "position": 249893126
        },
        {
            "id": 39,
            "top": 848008,
            "position": 239986264
        },
        {
            "id": 40,
            "top": 848008,
            "position": 128897216
        },
        {
            "id": 41,
            "top": 848008,
            "position": 139241389
        },
        {
            "id": 42,
            "top": 848008,
            "position": 67840640
        },
        {
            "id": 43,
            "top": 848008,
            "position": 116100167
        },
        {
            "id": 44,
            "top": 848008,
            "position": 87140204
        },
        {
            "id": 45,
            "top": 848008,
            "position": 150765351
        },
        {
            "id": 46,
            "top": 848008,
            "position": 115653472
        },
        {
            "id": 47,
            "top": 848008,
            "position": 182502686
        },
        {
            "id": 48,
            "top": 848008,
            "position": 44096504
        },
        {
            "id": 49,
            "top": 848008,
            "position": 141383012
        },
        {
            "id": 50,
            "top": 848008,
            "position": 194249622
        },
        {
            "id": 51,
            "top": 848008,
            "position": 166368315
        },
        {
            "id": 52,
            "top": 848008,
            "position": 154809608
        },
        {
            "id": 53,
            "top": 848008,
            "position": 26288248
        },
        {
            "id": 54,
            "top": 848008,
            "position": 122113152
        },
        {
            "id": 55,
            "top": 848008,
            "position": 152976581
        },
        {
            "id": 56,
            "top": 848008,
            "position": 151370604
        },
        {
            "id": 57,
            "top": 848008,
            "position": 38160360
        },
        {
            "id": 58,
            "top": 848008,
            "position": 182249269
        },
        {
            "id": 59,
            "top": 848008,
            "position": 272210568
        },
        {
            "id": 60,
            "top": 848008,
            "position": 118182966
        },
        {
            "id": 61,
            "top": 848008,
            "position": 260338456
        },
        {
            "id": 62,
            "top": 848008,
            "position": 318851008
        },
        {
            "id": 63,
            "top": 848008,
            "position": 278146624
        },
        {
            "id": 64,
            "top": 848008,
            "position": 61056576
        },
        {
            "id": 65,
            "top": 848008,
            "position": 162034508
        },
        {
            "id": 66,
            "top": 848008,
            "position": 109392576
        },
        {
            "id": 67,
            "top": 848008,
            "position": 175808119
        },
        {
            "id": 68,
            "top": 848008,
            "position": 196101850
        },
        {
            "id": 69,
            "top": 848008,
            "position": 39856376
        },
        {
            "id": 70,
            "top": 848008,
            "position": 33359582
        },
        {
            "id": 71,
            "top": 848008,
            "position": 106867512
        },
        {
            "id": 72,
            "top": 848008,
            "position": 317075694
        },
        {
            "id": 73,
            "top": 848008,
            "position": 178929688
        },
        {
            "id": 74,
            "top": 848008,
            "position": 32440379
        },
        {
            "id": 75,
            "top": 848008,
            "position": 168429544
        },
        {
            "id": 76,
            "top": 848008,
            "position": 284721345
        },
        {
            "id": 77,
            "top": 848008,
            "position": 165873318
        },
        {
            "id": 78,
            "top": 848008,
            "position": 87764128
        },
        {
            "id": 79,
            "top": 848008,
            "position": 108545024
        },
        {
            "id": 80,
            "top": 848008,
            "position": 173653695
        },
        {
            "id": 81,
            "top": 848008,
            "position": 61904584
        },
        {
            "id": 82,
            "top": 848008,
            "position": 163665677
        },
        {
            "id": 83,
            "top": 848008,
            "position": 63600588
        },
        {
            "id": 84,
            "top": 848008,
            "position": 104577474
        },
        {
            "id": 85,
            "top": 848008,
            "position": 158049198
        },
        {
            "id": 86,
            "top": 848008,
            "position": 172569765
        },
        {
            "id": 87,
            "top": 848008,
            "position": 153590328
        },
        {
            "id": 88,
            "top": 848008,
            "position": 173866664
        },
        {
            "id": 89,
            "top": 848008,
            "position": 147128872
        },
        {
            "id": 90,
            "top": 848008,
            "position": 187521348
        },
        {
            "id": 91,
            "top": 848008,
            "position": 299346824
        },
        {
            "id": 92,
            "top": 848008,
            "position": 195889848
        },
        {
            "id": 93,
            "top": 848008,
            "position": 106082573
        },
        {
            "id": 94,
            "top": 848008,
            "position": 176729129
        },
        {
            "id": 95,
            "top": 848008,
            "position": 169011675
        },
        {
            "id": 96,
            "top": 848008,
            "position": 158932525
        },
        {
            "id": 97,
            "top": 848008,
            "position": 66144624
        },
        {
            "id": 98,
            "top": 848008,
            "position": 47792390
        },
        {
            "id": 99,
            "top": 848008,
            "position": 166442481
        },
        {
            "id": 100,
            "top": 848008,
            "position": 113632827
        },
        {
            "id": 101,
            "top": 848008,
            "position": 27136256
        },
        {
            "id": 102,
            "top": 848008,
            "position": 171252938
        },
        {
            "id": 103,
            "top": 848008,
            "position": 255290850
        },
        {
            "id": 104,
            "top": 848008,
            "position": 108966749
        },
        {
            "id": 105,
            "top": 848008,
            "position": 174313866
        },
        {
            "id": 106,
            "top": 848008,
            "position": 194593070
        },
        {
            "id": 107,
            "top": 848008,
            "position": 165822975
        },
        {
            "id": 108,
            "top": 848008,
            "position": 175969905
        },
        {
            "id": 109,
            "top": 848008,
            "position": 171297616
        },
        {
            "id": 110,
            "top": 848008,
            "position": 124434302
        },
        {
            "id": 111,
            "top": 848008,
            "position": 79288668
        },
        {
            "id": 112,
            "top": 848008,
            "position": 150432156
        },
        {
            "id": 113,
            "top": 848008,
            "position": 120268775
        },
        {
            "id": 114,
            "top": 848008,
            "position": 86921024
        },
        {
            "id": 115,
            "top": 848008,
            "position": 133561008
        },
        {
            "id": 116,
            "top": 848008,
            "position": 97793597
        },
        {
            "id": 117,
            "top": 848008,
            "position": 116967448
        },
        {
            "id": 118,
            "top": 848008,
            "position": 177489436
        },
        {
            "id": 119,
            "top": 848008,
            "position": 130451863
        },
        {
            "id": 120,
            "top": 848008,
            "position": 183119640
        },
        {
            "id": 121,
            "top": 848008,
            "position": 79712972
        },
        {
            "id": 122,
            "top": 848008,
            "position": 149002671
        },
        {
            "id": 123,
            "top": 848008,
            "position": 194702583
        },
        {
            "id": 124,
            "top": 848008,
            "position": 97520920
        },
        {
            "id": 125,
            "top": 848008,
            "position": 154034937
        },
        {
            "id": 126,
            "top": 848008,
            "position": 72158711
        },
        {
            "id": 127,
            "top": 848008,
            "position": 74624704
        },
        {
            "id": 128,
            "top": 848008,
            "position": 58512552
        },
        {
            "id": 129,
            "top": 848008,
            "position": 140925908
        },
        {
            "id": 130,
            "top": 848008,
            "position": 154942980
        },
        {
            "id": 131,
            "top": 848008,
            "position": 211153992
        },
        {
            "id": 132,
            "top": 848008,
            "position": 94128888
        },
        {
            "id": 133,
            "top": 848008,
            "position": 191649808
        },
        {
            "id": 134,
            "top": 848008,
            "position": 164511619
        },
        {
            "id": 135,
            "top": 848008,
            "position": 95824904
        },
        {
            "id": 136,
            "top": 848008,
            "position": 157244912
        },
        {
            "id": 137,
            "top": 848008,
            "position": 264578496
        },
        {
            "id": 138,
            "top": 848008,
            "position": 145404712
        },
        {
            "id": 139,
            "top": 848008,
            "position": 105154196
        },
        {
            "id": 140,
            "top": 848008,
            "position": 177570060
        },
        {
            "id": 141,
            "top": 848008,
            "position": 73101512
        },
        {
            "id": 142,
            "top": 848008,
            "position": 41128388
        },
        {
            "id": 143,
            "top": 848008,
            "position": 170516705
        },
        {
            "id": 144,
            "top": 848008,
            "position": 157214354
        },
        {
            "id": 145,
            "top": 848008,
            "position": 60208568
        },
        {
            "id": 146,
            "top": 848008,
            "position": 171627341
        },
        {
            "id": 147,
            "top": 848008,
            "position": 125505184
        },
        {
            "id": 148,
            "top": 848008,
            "position": 179720795
        },
        {
            "id": 149,
            "top": 848008,
            "position": 162656958
        },
        {
            "id": 150,
            "top": 848008,
            "position": 138999889
        },
        {
            "id": 151,
            "top": 848008,
            "position": 212850008
        },
        {
            "id": 152,
            "top": 848008,
            "position": 163548140
        },
        {
            "id": 153,
            "top": 848008,
            "position": 64024726
        },
        {
            "id": 154,
            "top": 848008,
            "position": 95400396
        },
        {
            "id": 155,
            "top": 848008,
            "position": 220590256
        },
        {
            "id": 156,
            "top": 848008,
            "position": 179683424
        },
        {
            "id": 157,
            "top": 848008,
            "position": 174445922
        },
        {
            "id": 158,
            "top": 848008,
            "position": 16960160
        },
        {
            "id": 159,
            "top": 848008,
            "position": 140931777
        },
        {
            "id": 160,
            "top": 848008,
            "position": 155043066
        },
        {
            "id": 161,
            "top": 848008,
            "position": 80985248
        },
        {
            "id": 162,
            "top": 848008,
            "position": 161162787
        },
        {
            "id": 163,
            "top": 848008,
            "position": 187409768
        },
        {
            "id": 164,
            "top": 848008,
            "position": 166209050
        },
        {
            "id": 165,
            "top": 848008,
            "position": 18656176
        },
        {
            "id": 166,
            "top": 848008,
            "position": 270269990
        },
        {
            "id": 167,
            "top": 848008,
            "position": 155650165
        },
        {
            "id": 168,
            "top": 848008,
            "position": 113663037
        },
        {
            "id": 169,
            "top": 848008,
            "position": 174583325
        },
        {
            "id": 170,
            "top": 848008,
            "position": 163236372
        },
        {
            "id": 171,
            "top": 848008,
            "position": 225520906
        },
        {
            "id": 172,
            "top": 848008,
            "position": 90310447
        },
        {
            "id": 173,
            "top": 848008,
            "position": 128049856
        },
        {
            "id": 174,
            "top": 848008,
            "position": 113180643
        },
        {
            "id": 175,
            "top": 848008,
            "position": 165362106
        },
        {
            "id": 176,
            "top": 848008,
            "position": 175785602
        },
        {
            "id": 177,
            "top": 848008,
            "position": 90102916
        },
        {
            "id": 178,
            "top": 848008,
            "position": 159990793
        },
        {
            "id": 179,
            "top": 848008,
            "position": 174878320
        },
        {
            "id": 180,
            "top": 848008,
            "position": 172175597
        },
        {
            "id": 181,
            "top": 848008,
            "position": 169722744
        },
        {
            "id": 182,
            "top": 848008,
            "position": 148826412
        },
        {
            "id": 183,
            "top": 848008,
            "position": 153061889
        },
        {
            "id": 184,
            "top": 848008,
            "position": 115329088
        },
        {
            "id": 185,
            "top": 848008,
            "position": 113081708
        },
        {
            "id": 186,
            "top": 848008,
            "position": 237442240
        },
        {
            "id": 187,
            "top": 848008,
            "position": 234898216
        },
        {
            "id": 188,
            "top": 848008,
            "position": 75472936
        },
        {
            "id": 189,
            "top": 848008,
            "position": 294258776
        },
        {
            "id": 190,
            "top": 848008,
            "position": 132690994
        },
        {
            "id": 191,
            "top": 848008,
            "position": 29680245
        },
        {
            "id": 192,
            "top": 848008,
            "position": 141755862
        },
        {
            "id": 193,
            "top": 848008,
            "position": 176001379
        },
        {
            "id": 194,
            "top": 848008,
            "position": 143066517
        },
        {
            "id": 195,
            "top": 848008,
            "position": 80081958
        },
        {
            "id": 196,
            "top": 848008,
            "position": 177362797
        },
        {
            "id": 197,
            "top": 848008,
            "position": 164513238
        },
        {
            "id": 198,
            "top": 848008,
            "position": 99640680
        },
        {
            "id": 199,
            "top": 848008,
            "position": 314610968
        },
        {
            "id": 200,
            "top": 848008,
            "position": 143723076
        },
        {
            "id": 201,
            "top": 848008,
            "position": 131257283
        },
        {
            "id": 202,
            "top": 848008,
            "position": 55968528
        },
        {
            "id": 203,
            "top": 848008,
            "position": 242773722
        },
        {
            "id": 204,
            "top": 848008,
            "position": 169554290
        },
        {
            "id": 205,
            "top": 848008,
            "position": 83713816
        },
        {
            "id": 206,
            "top": 848008,
            "position": 90736665
        },
        {
            "id": 207,
            "top": 848008,
            "position": 103455688
        },
        {
            "id": 208,
            "top": 848008,
            "position": 126944200
        },
        {
            "id": 209,
            "top": 848008,
            "position": 168515940
        },
        {
            "id": 210,
            "top": 848008,
            "position": 247476312
        },
        {
            "id": 211,
            "top": 848008,
            "position": 117134627
        },
        {
            "id": 212,
            "top": 848008,
            "position": 126353192
        },
        {
            "id": 213,
            "top": 848008,
            "position": 85648832
        },
        {
            "id": 214,
            "top": 848008,
            "position": 156901265
        },
        {
            "id": 215,
            "top": 848008,
            "position": 109393032
        },
        {
            "id": 216,
            "top": 848008,
            "position": 39432372
        },
        {
            "id": 217,
            "top": 848008,
            "position": 87953268
        },
        {
            "id": 218,
            "top": 848008,
            "position": 128049208
        },
        {
            "id": 219,
            "top": 848008,
            "position": 143738096
        },
        {
            "id": 220,
            "top": 848008,
            "position": 196450489
        },
        {
            "id": 221,
            "top": 848008,
            "position": 74049775
        },
        {
            "id": 222,
            "top": 848008,
            "position": 162863018
        },
        {
            "id": 223,
            "top": 848008,
            "position": 116177688
        },
        {
            "id": 224,
            "top": 848008,
            "position": 170771534
        },
        {
            "id": 225,
            "top": 848008,
            "position": 187209327
        },
        {
            "id": 226,
            "top": 848008,
            "position": 120416776
        },
        {
            "id": 227,
            "top": 848008,
            "position": 44520371
        },
        {
            "id": 228,
            "top": 848008,
            "position": 175934257
        },
        {
            "id": 229,
            "top": 848008,
            "position": 159637506
        },
        {
            "id": 230,
            "top": 848008,
            "position": 118298036
        },
        {
            "id": 231,
            "top": 848008,
            "position": 118674829
        },
        {
            "id": 232,
            "top": 848008,
            "position": 196625283
        },
        {
            "id": 233,
            "top": 848008,
            "position": 164476201
        },
        {
            "id": 234,
            "top": 848008,
            "position": 251858376
        },
        {
            "id": 235,
            "top": 848008,
            "position": 158429955
        },
        {
            "id": 236,
            "top": 848008,
            "position": 81832772
        },
        {
            "id": 237,
            "top": 848008,
            "position": 16112152
        },
        {
            "id": 238,
            "top": 848008,
            "position": 96248676
        },
        {
            "id": 239,
            "top": 848008,
            "position": 176653456
        },
        {
            "id": 240,
            "top": 848008,
            "position": 229810168
        },
        {
            "id": 241,
            "top": 848008,
            "position": 207719680
        },
        {
            "id": 242,
            "top": 848008,
            "position": 146242425
        },
        {
            "id": 243,
            "top": 848008,
            "position": 75048912
        },
        {
            "id": 244,
            "top": 848008,
            "position": 132289248
        },
        {
            "id": 245,
            "top": 848008,
            "position": 89562588
        },
        {
            "id": 246,
            "top": 848008,
            "position": 180727310
        },
        {
            "id": 247,
            "top": 848008,
            "position": 163529515
        },
        {
            "id": 248,
            "top": 848008,
            "position": 123809168
        },
        {
            "id": 249,
            "top": 848008,
            "position": 152217120
        },
        {
            "id": 250,
            "top": 848008,
            "position": 227266144
        },
        {
            "id": 251,
            "top": 848008,
            "position": 163671704
        },
        {
            "id": 252,
            "top": 848008,
            "position": 319699016
        },
        {
            "id": 253,
            "top": 848008,
            "position": 221358512
        },
        {
            "id": 254,
            "top": 848008,
            "position": 206065944
        },
        {
            "id": 255,
            "top": 848008,
            "position": 54953521
        },
        {
            "id": 256,
            "top": 848008,
            "position": 174405004
        },
        {
            "id": 257,
            "top": 848008,
            "position": 158834951
        },
        {
            "id": 258,
            "top": 848008,
            "position": 159444884
        },
        {
            "id": 259,
            "top": 848008,
            "position": 116136724
        },
        {
            "id": 260,
            "top": 848008,
            "position": 138225304
        },
        {
            "id": 261,
            "top": 848008,
            "position": 202524594
        },
        {
            "id": 262,
            "top": 848008,
            "position": 203521920
        },
        {
            "id": 263,
            "top": 848008,
            "position": 70809494
        },
        {
            "id": 264,
            "top": 848008,
            "position": 111937056
        },
        {
            "id": 265,
            "top": 848008,
            "position": 194745863
        },
        {
            "id": 266,
            "top": 848008,
            "position": 65274483
        },
        {
            "id": 267,
            "top": 848008,
            "position": 174592100
        },
        {
            "id": 268,
            "top": 848008,
            "position": 153581956
        },
        {
            "id": 269,
            "top": 848008,
            "position": 45792432
        },
        {
            "id": 270,
            "top": 848008,
            "position": 158752813
        },
        {
            "id": 271,
            "top": 848008,
            "position": 186561760
        },
        {
            "id": 272,
            "top": 848008,
            "position": 219634072
        },
        {
            "id": 273,
            "top": 848008,
            "position": 182160937
        },
        {
            "id": 274,
            "top": 848008,
            "position": 90312804
        },
        {
            "id": 275,
            "top": 848008,
            "position": 61480512
        },
        {
            "id": 276,
            "top": 848008,
            "position": 283234672
        },
        {
            "id": 277,
            "top": 848008,
            "position": 156881480
        },
        {
            "id": 278,
            "top": 848008,
            "position": 73727046
        },
        {
            "id": 279,
            "top": 848008,
            "position": 106001720
        },
        {
            "id": 280,
            "top": 848008,
            "position": 66144762
        },
        {
            "id": 281,
            "top": 848008,
            "position": 61056576
        },
        {
            "id": 282,
            "top": 848008,
            "position": 101883674
        },
        {
            "id": 283,
            "top": 848008,
            "position": 318003000
        },
        {
            "id": 284,
            "top": 848008,
            "position": 185565652
        },
        {
            "id": 285,
            "top": 848008,
            "position": 119793114
        },
        {
            "id": 286,
            "top": 848008,
            "position": 147976092
        },
        {
            "id": 287,
            "top": 848008,
            "position": 62752592
        },
        {
            "id": 288,
            "top": 848008,
            "position": 72928688
        },
        {
            "id": 289,
            "top": 848008,
            "position": 55968324
        },
        {
            "id": 290,
            "top": 848008,
            "position": 165106985
        },
        {
            "id": 291,
            "top": 848008,
            "position": 85648528
        },
        {
            "id": 292,
            "top": 848008,
            "position": 25440240
        },
        {
            "id": 293,
            "top": 848008,
            "position": 166698688
        },
        {
            "id": 294,
            "top": 848008,
            "position": 173878865
        },
        {
            "id": 295,
            "top": 848008,
            "position": 22896216
        },
        {
            "id": 296,
            "top": 848008,
            "position": 108142467
        },
        {
            "id": 297,
            "top": 848008,
            "position": 84628283
        },
        {
            "id": 298,
            "top": 848008,
            "position": 162676181
        },
        {
            "id": 299,
            "top": 848008,
            "position": 111513292
        },
        {
            "id": 300,
            "top": 848008,
            "position": 82986777
        },
        {
            "id": 301,
            "top": 848008,
            "position": 167607730
        },
        {
            "id": 302,
            "top": 848008,
            "position": 91017789
        },
        {
            "id": 303,
            "top": 848008,
            "position": 118114570
        },
        {
            "id": 304,
            "top": 848008,
            "position": 200977896
        },
        {
            "id": 305,
            "top": 848008,
            "position": 99883073
        },
        {
            "id": 306,
            "top": 848008,
            "position": 20352170
        },
        {
            "id": 307,
            "top": 848008,
            "position": 155112082
        },
        {
            "id": 308,
            "top": 848008,
            "position": 324787064
        },
        {
            "id": 309,
            "top": 848008,
            "position": 222178096
        },
        {
            "id": 310,
            "top": 848008,
            "position": 178929688
        },
        {
            "id": 311,
            "top": 848008,
            "position": 144373456
        },
        {
            "id": 312,
            "top": 848008,
            "position": 59784120
        },
        {
            "id": 313,
            "top": 848008,
            "position": 71656708
        },
        {
            "id": 314,
            "top": 848008,
            "position": 158110422
        },
        {
            "id": 315,
            "top": 848008,
            "position": 77017716
        },
        {
            "id": 316,
            "top": 848008,
            "position": 126349876
        },
        {
            "id": 317,
            "top": 848008,
            "position": 164020804
        },
        {
            "id": 318,
            "top": 848008,
            "position": 179372618
        },
        {
            "id": 319,
            "top": 848008,
            "position": 94605456
        },
        {
            "id": 320,
            "top": 848008,
            "position": 295954792
        },
        {
            "id": 321,
            "top": 848008,
            "position": 80984764
        },
        {
            "id": 322,
            "top": 848008,
            "position": 169145183
        },
        {
            "id": 323,
            "top": 848008,
            "position": 307826904
        },
        {
            "id": 324,
            "top": 848008,
            "position": 150351989
        },
        {
            "id": 325,
            "top": 848008,
            "position": 85113764
        },
        {
            "id": 326,
            "top": 848008,
            "position": 35616364
        },
        {
            "id": 327,
            "top": 848008,
            "position": 189986124
        },
        {
            "id": 328,
            "top": 848008,
            "position": 151403653
        },
        {
            "id": 329,
            "top": 848008,
            "position": 170818618
        },
        {
            "id": 330,
            "top": 848008,
            "position": 155639294
        },
        {
            "id": 331,
            "top": 848008,
            "position": 187246511
        },
        {
            "id": 332,
            "top": 848008,
            "position": 102093531
        },
        {
            "id": 333,
            "top": 848008,
            "position": 214546024
        },
        {
            "id": 334,
            "top": 848008,
            "position": 130593232
        },
        {
            "id": 335,
            "top": 848008,
            "position": 38160360
        },
        {
            "id": 336,
            "top": 848008,
            "position": 235746224
        },
        {
            "id": 337,
            "top": 848008,
            "position": 178280560
        },
        {
            "id": 338,
            "top": 848008,
            "position": 92916066
        },
        {
            "id": 339,
            "top": 848008,
            "position": 114905384
        },
        {
            "id": 340,
            "top": 848008,
            "position": 186388695
        },
        {
            "id": 341,
            "top": 848008,
            "position": 26288192
        },
        {
            "id": 342,
            "top": 848008,
            "position": 109392704
        },
        {
            "id": 343,
            "top": 848008,
            "position": 142574479
        },
        {
            "id": 344,
            "top": 848008,
            "position": 56557290
        },
        {
            "id": 345,
            "top": 848008,
            "position": 160645774
        },
        {
            "id": 346,
            "top": 848008,
            "position": 158769808
        },
        {
            "id": 347,
            "top": 848008,
            "position": 98080145
        },
        {
            "id": 348,
            "top": 848008,
            "position": 155503467
        },
        {
            "id": 349,
            "top": 848008,
            "position": 7632072
        },
        {
            "id": 350,
            "top": 848008,
            "position": 180816380
        },
        {
            "id": 351,
            "top": 848008,
            "position": 146234232
        },
        {
            "id": 352,
            "top": 848008,
            "position": 167927586
        },
        {
            "id": 353,
            "top": 848008,
            "position": 78016772
        },
        {
            "id": 354,
            "top": 848008,
            "position": 145735366
        },
        {
            "id": 355,
            "top": 848008,
            "position": 164320846
        },
        {
            "id": 356,
            "top": 848008,
            "position": 171766118
        },
        {
            "id": 357,
            "top": 848008,
            "position": 130073770
        },
        {
            "id": 358,
            "top": 848008,
            "position": 84538600
        },
        {
            "id": 359,
            "top": 848008,
            "position": 70384916
        },
        {
            "id": 360,
            "top": 848008,
            "position": 41002738
        },
        {
            "id": 361,
            "top": 848008,
            "position": 161121520
        },
        {
            "id": 362,
            "top": 848008,
            "position": 164201029
        },
        {
            "id": 363,
            "top": 848008,
            "position": 114511953
        },
        {
            "id": 364,
            "top": 848008,
            "position": 284082680
        },
        {
            "id": 365,
            "top": 848008,
            "position": 183842819
        },
        {
            "id": 366,
            "top": 848008,
            "position": 93281144
        },
        {
            "id": 367,
            "top": 848008,
            "position": 14416136
        },
        {
            "id": 368,
            "top": 848008,
            "position": 222178096
        },
        {
            "id": 369,
            "top": 848008,
            "position": 85166260
        },
        {
            "id": 370,
            "top": 848008,
            "position": 125929956
        },
        {
            "id": 371,
            "top": 848008,
            "position": 259490448
        },
        {
            "id": 372,
            "top": 848008,
            "position": 182321852
        },
        {
            "id": 373,
            "top": 848008,
            "position": 110145451
        },
        {
            "id": 374,
            "top": 848008,
            "position": 102488246
        },
        {
            "id": 375,
            "top": 848008,
            "position": 146704428
        },
        {
            "id": 376,
            "top": 848008,
            "position": 116600766
        },
        {
            "id": 377,
            "top": 848008,
            "position": 188744700
        },
        {
            "id": 378,
            "top": 848008,
            "position": 171417141
        },
        {
            "id": 379,
            "top": 848008,
            "position": 257008428
        },
        {
            "id": 380,
            "top": 848008,
            "position": 89594608
        },
        {
            "id": 381,
            "top": 848008,
            "position": 161969528
        },
        {
            "id": 382,
            "top": 848008,
            "position": 84800800
        },
        {
            "id": 383,
            "top": 848008,
            "position": 186822828
        },
        {
            "id": 384,
            "top": 848008,
            "position": 64448936
        },
        {
            "id": 385,
            "top": 848008,
            "position": 91161412
        },
        {
            "id": 386,
            "top": 848008,
            "position": 88760989
        },
        {
            "id": 387,
            "top": 848008,
            "position": 125383254
        },
        {
            "id": 388,
            "top": 848008,
            "position": 178562742
        },
        {
            "id": 389,
            "top": 848008,
            "position": 303586864
        },
        {
            "id": 390,
            "top": 848008,
            "position": 245074312
        },
        {
            "id": 391,
            "top": 848008,
            "position": 175231097
        },
        {
            "id": 392,
            "top": 848008,
            "position": 101375655
        },
        {
            "id": 393,
            "top": 848008,
            "position": 208738156
        },
        {
            "id": 394,
            "top": 848008,
            "position": 339203200
        },
        {
            "id": 395,
            "top": 848008,
            "position": 223207107
        },
        {
            "id": 396,
            "top": 848008,
            "position": 181473712
        },
        {
            "id": 397,
            "top": 848008,
            "position": 157088178
        },
        {
            "id": 398,
            "top": 848008,
            "position": 120104298
        },
        {
            "id": 399,
            "top": 848008,
            "position": 124233494
        },
        {
            "id": 400,
            "top": 848008,
            "position": 171490974
        },
        {
            "id": 401,
            "top": 848008,
            "position": 103449044
        },
        {
            "id": 402,
            "top": 848008,
            "position": 173841640
        },
        {
            "id": 403,
            "top": 848008,
            "position": 66169867
        },
        {
            "id": 404,
            "top": 848008,
            "position": 178030901
        },
        {
            "id": 405,
            "top": 848008,
            "position": 107423042
        },
        {
            "id": 406,
            "top": 848008,
            "position": 113295380
        },
        {
            "id": 407,
            "top": 848008,
            "position": 97944638
        },
        {
            "id": 408,
            "top": 848008,
            "position": 197323380
        },
        {
            "id": 409,
            "top": 848008,
            "position": 164799037
        },
        {
            "id": 410,
            "top": 848008,
            "position": 164870608
        },
        {
            "id": 411,
            "top": 848008,
            "position": 172707918
        },
        {
            "id": 412,
            "top": 848008,
            "position": 152372289
        },
        {
            "id": 413,
            "top": 848008,
            "position": 37736356
        },
        {
            "id": 414,
            "top": 848008,
            "position": 117872660
        },
        {
            "id": 415,
            "top": 848008,
            "position": 157860197
        },
        {
            "id": 416,
            "top": 848008,
            "position": 97096540
        },
        {
            "id": 417,
            "top": 848008,
            "position": 18656176
        },
        {
            "id": 418,
            "top": 848008,
            "position": 147973570
        },
        {
            "id": 419,
            "top": 848008,
            "position": 164989529
        },
        {
            "id": 420,
            "top": 848008,
            "position": 142889887
        },
        {
            "id": 421,
            "top": 848008,
            "position": 237553679
        },
        {
            "id": 422,
            "top": 848008,
            "position": 89187304
        },
        {
            "id": 423,
            "top": 848008,
            "position": 62752652
        },
        {
            "id": 424,
            "top": 848008,
            "position": 56816362
        },
        {
            "id": 425,
            "top": 848008,
            "position": 106851024
        },
        {
            "id": 426,
            "top": 848008,
            "position": 155772567
        },
        {
            "id": 427,
            "top": 848008,
            "position": 195790757
        },
        {
            "id": 428,
            "top": 848008,
            "position": 154335510
        },
        {
            "id": 429,
            "top": 848008,
            "position": 137457819
        },
        {
            "id": 430,
            "top": 848008,
            "position": 180984232
        },
        {
            "id": 431,
            "top": 848008,
            "position": 169968499
        },
        {
            "id": 432,
            "top": 848008,
            "position": 110241040
        },
        {
            "id": 433,
            "top": 848008,
            "position": 152293002
        },
        {
            "id": 434,
            "top": 848008,
            "position": 180248864
        },
        {
            "id": 435,
            "top": 848008,
            "position": 101337212
        },
        {
            "id": 436,
            "top": 848008,
            "position": 292562760
        },
        {
            "id": 437,
            "top": 848008,
            "position": 134919824
        },
        {
            "id": 438,
            "top": 848008,
            "position": 178215813
        },
        {
            "id": 439,
            "top": 848008,
            "position": 120351635
        },
        {
            "id": 440,
            "top": 848008,
            "position": 100947042
        },
        {
            "id": 441,
            "top": 848008,
            "position": 218927312
        },
        {
            "id": 442,
            "top": 848008,
            "position": 107273268
        },
        {
            "id": 443,
            "top": 848008,
            "position": 103815205
        },
        {
            "id": 444,
            "top": 848008,
            "position": 145857075
        },
        {
            "id": 445,
            "top": 848008,
            "position": 141606057
        },
        {
            "id": 446,
            "top": 848008,
            "position": 106001000
        },
        {
            "id": 447,
            "top": 848008,
            "position": 197419937
        },
        {
            "id": 448,
            "top": 848008,
            "position": 115738039
        },
        {
            "id": 449,
            "top": 848008,
            "position": 84800800
        },
        {
            "id": 450,
            "top": 848008,
            "position": 126808447
        },
        {
            "id": 451,
            "top": 848008,
            "position": 163288823
        },
        {
            "id": 452,
            "top": 848008,
            "position": 53848354
        },
        {
            "id": 453,
            "top": 848008,
            "position": 50032472
        },
        {
            "id": 454,
            "top": 848008,
            "position": 145047604
        },
        {
            "id": 455,
            "top": 848008,
            "position": 117024708
        },
        {
            "id": 456,
            "top": 848008,
            "position": 285778696
        },
        {
            "id": 457,
            "top": 848008,
            "position": 150298075
        },
        {
            "id": 458,
            "top": 848008,
            "position": 186084463
        },
        {
            "id": 459,
            "top": 848008,
            "position": 176375723
        },
        {
            "id": 460,
            "top": 848008,
            "position": 147552880
        },
        {
            "id": 461,
            "top": 848008,
            "position": 154335926
        },
        {
            "id": 462,
            "top": 848008,
            "position": 185064665
        },
        {
            "id": 463,
            "top": 848008,
            "position": 150007220
        },
        {
            "id": 464,
            "top": 848008,
            "position": 164628729
        },
        {
            "id": 465,
            "top": 848008,
            "position": 100217254
        },
        {
            "id": 466,
            "top": 848008,
            "position": 189953792
        },
        {
            "id": 467,
            "top": 848008,
            "position": 170724493
        },
        {
            "id": 468,
            "top": 848008,
            "position": 223191842
        },
        {
            "id": 469,
            "top": 848008,
            "position": 66992424
        },
        {
            "id": 470,
            "top": 848008,
            "position": 117449404
        },
        {
            "id": 471,
            "top": 848008,
            "position": 55969608
        },
        {
            "id": 472,
            "top": 848008,
            "position": 137955480
        },
        {
            "id": 473,
            "top": 848008,
            "position": 105527016
        },
        {
            "id": 474,
            "top": 848008,
            "position": 125928864
        },
        {
            "id": 475,
            "top": 848008,
            "position": 134270890
        },
        {
            "id": 476,
            "top": 848008,
            "position": 160273512
        },
        {
            "id": 477,
            "top": 848008,
            "position": 228962160
        },
        {
            "id": 478,
            "top": 848008,
            "position": 60208568
        },
        {
            "id": 479,
            "top": 848008,
            "position": 52576336
        },
        {
            "id": 480,
            "top": 848008,
            "position": 160775526
        },
        {
            "id": 481,
            "top": 848008,
            "position": 78016736
        },
        {
            "id": 482,
            "top": 848008,
            "position": 178482207
        },
        {
            "id": 483,
            "top": 848008,
            "position": 135679720
        },
        {
            "id": 484,
            "top": 848008,
            "position": 21624171
        },
        {
            "id": 485,
            "top": 848008,
            "position": 178535766
        },
        {
            "id": 486,
            "top": 848008,
            "position": 241682280
        },
        {
            "id": 487,
            "top": 848008,
            "position": 92856940
        },
        {
            "id": 488,
            "top": 848008,
            "position": 102762701
        },
        {
            "id": 489,
            "top": 848008,
            "position": 129382970
        },
        {
            "id": 490,
            "top": 848008,
            "position": 172053312
        },
        {
            "id": 491,
            "top": 848008,
            "position": 100064944
        },
        {
            "id": 492,
            "top": 848008,
            "position": 172695145
        },
        {
            "id": 493,
            "top": 848008,
            "position": 321395032
        },
        {
            "id": 494,
            "top": 848008,
            "position": 193499982
        },
        {
            "id": 495,
            "top": 848008,
            "position": 131441240
        },
        {
            "id": 496,
            "top": 848008,
            "position": 148709701
        },
        {
            "id": 497,
            "top": 848008,
            "position": 160989176
        },
        {
            "id": 498,
            "top": 848008,
            "position": 239304212
        },
        {
            "id": 499,
            "top": 848008,
            "position": 177852929
        }
    ],
    "qualite": 0.8443985931331779,
    "temperature": -5.817388756774031
}