{
    "tortoises": [
        {
            "id": 0,
            "top": 676062,
            "position": 110696728
        },
        {
            "id": 1,
            "top": 676062,
            "position": 93103545
        },
        {
            "id": 2,
            "top": 676062,
            "position": 119307444
        },
        {
            "id": 3,
            "top": 676062,
            "position": 182881048
        },
        {
            "id": 4,
            "top": 676062,
            "position": 139655311
        },
        {
            "id": 5,
            "top": 676062,
            "position": 86312558
        },
        {
            "id": 6,
            "top": 676062,
            "position": 137557945
        },
        {
            "id": 7,
            "top": 676062,
            "position": 184698978
        },
        {
            "id": 8,
            "top": 676062,
            "position": 260283870
        },
        {
            "id": 9,
            "top": 676062,
            "position": 159385945
        },
        {
            "id": 10,
            "top": 676062,
            "position": 59493456
        },
        {
            "id": 11,
            "top": 676062,
            "position": 143044529
        },
        {
            "id": 12,
            "top": 676062,
            "position": 89577279
        },
        {
            "id": 13,
            "top": 676062,
            "position": 237973824
        },
        {
            "id": 14,
            "top": 676062,
            "position": 109860573
        },
        {
            "id": 15,
            "top": 676062,
            "position": 134057436
        },
        {
            "id": 16,
            "top": 676062,
            "position": 92423715
        },
        {
            "id": 17,
            "top": 676062,
            "position": 134875707
        },
        {
            "id": 18,
            "top": 676062,
            "position": 108088617
        },
        {
            "id": 19,
            "top": 676062,
            "position": 111652581
        },
        {
            "id": 20,
            "top": 676062,
            "position": 143795448
        },
        {
            "id": 21,
            "top": 676062,
            "position": 118281693
        },
        {
            "id": 22,
            "top": 676062,
            "position": 127437368
        },
        {
            "id": 23,
            "top": 676062,
            "position": 40901664
        },
        {
            "id": 24,
            "top": 676062,
            "position": 84674938
        },
        {
            "id": 25,
            "top": 676062,
            "position": 139665559
        },
        {
            "id": 26,
            "top": 676062,
            "position": 108253441
        },
        {
            "id": 27,
            "top": 676062,
            "position": 133156020
        },
        {
            "id": 28,
            "top": 676062,
            "position": 113619628
        },
        {
            "id": 29,
            "top": 676062,
            "position": 121046488
        },
        {
            "id": 30,
            "top": 676062,
            "position": 29746812
        },
        {
            "id": 31,
            "top": 676062,
            "position": 60995838
        },
        {
            "id": 32,
            "top": 676062,
            "position": 113645833
        },
        {
            "id": 33,
            "top": 676062,
            "position": 49357693
        },
        {
            "id": 34,
            "top": 676062,
            "position": 83155626
        },
        {
            "id": 35,
            "top": 676062,
            "position": 132815370
        },
        {
            "id": 36,
            "top": 676062,
            "position": 196358526
        },
        {
            "id": 37,
            "top": 676062,
            "position": 128550977
        },
        {
            "id": 38,
            "top": 676062,
            "position": 190227864
        },
        {
            "id": 39,
            "top": 676062,
            "position": 191325546
        },
        {
            "id": 40,
            "top": 676062,
            "position": 102761424
        },
        {
            "id": 41,
            "top": 676062,
            "position": 115030485
        },
        {
            "id": 42,
            "top": 676062,
            "position": 54085095
        },
        {
            "id": 43,
            "top": 676062,
            "position": 80582340
        },
        {
            "id": 44,
            "top": 676062,
            "position": 64138127
        },
        {
            "id": 45,
            "top": 676062,
            "position": 103136309
        },
        {
            "id": 46,
            "top": 676062,
            "position": 84783086
        },
        {
            "id": 47,
            "top": 676062,
            "position": 145497591
        },
        {
            "id": 48,
            "top": 676062,
            "position": 35155236
        },
        {
            "id": 49,
            "top": 676062,
            "position": 115217259
        },
        {
            "id": 50,
            "top": 676062,
            "position": 154862856
        },
        {
            "id": 51,
            "top": 676062,
            "position": 132634219
        },
        {
            "id": 52,
            "top": 676062,
            "position": 149135327
        },
        {
            "id": 53,
            "top": 676062,
            "position": 20957922
        },
        {
            "id": 54,
            "top": 676062,
            "position": 97352928
        },
        {
            "id": 55,
            "top": 676062,
            "position": 121957776
        },
        {
            "id": 56,
            "top": 676062,
            "position": 120675339
        },
        {
            "id": 57,
            "top": 676062,
            "position": 30422745
        },
        {
            "id": 58,
            "top": 676062,
            "position": 145295314
        },
        {
            "id": 59,
            "top": 676062,
            "position": 217015902
        },
        {
            "id": 60,
            "top": 676062,
            "position": 95598045
        },
        {
            "id": 61,
            "top": 676062,
            "position": 207551034
        },
        {
            "id": 62,
            "top": 676062,
            "position": 254199312
        },
        {
            "id": 63,
            "top": 676062,
            "position": 221748336
        },
        {
            "id": 64,
            "top": 676062,
            "position": 48676464
        },
        {
            "id": 65,
            "top": 676062,
            "position": 129498314
        },
        {
            "id": 66,
            "top": 676062,
            "position": 87213342
        },
        {
            "id": 67,
            "top": 676062,
            "position": 140021340
        },
        {
            "id": 68,
            "top": 676062,
            "position": 156339319
        },
        {
            "id": 69,
            "top": 676062,
            "position": 31774914
        },
        {
            "id": 70,
            "top": 676062,
            "position": 23988841
        },
        {
            "id": 71,
            "top": 676062,
            "position": 76861866
        },
        {
            "id": 72,
            "top": 676062,
            "position": 249328970
        },
        {
            "id": 73,
            "top": 676062,
            "position": 142649082
        },
        {
            "id": 74,
            "top": 676062,
            "position": 26680214
        },
        {
            "id": 75,
            "top": 676062,
            "position": 133271896
        },
        {
            "id": 76,
            "top": 676062,
            "position": 220413541
        },
        {
            "id": 77,
            "top": 676062,
            "position": 132240085
        },
        {
            "id": 78,
            "top": 676062,
            "position": 80886248
        },
        {
            "id": 79,
            "top": 676062,
            "position": 86535936
        },
        {
            "id": 80,
            "top": 676062,
            "position": 138443058
        },
        {
            "id": 81,
            "top": 676062,
            "position": 49352526
        },
        {
            "id": 82,
            "top": 676062,
            "position": 130479857
        },
        {
            "id": 83,
            "top": 676062,
            "position": 50704650
        },
        {
            "id": 84,
            "top": 676062,
            "position": 82382589
        },
        {
            "id": 85,
            "top": 676062,
            "position": 126002318
        },
        {
            "id": 86,
            "top": 676062,
            "position": 137578718
        },
        {
            "id": 87,
            "top": 676062,
            "position": 128956852
        },
        {
            "id": 88,
            "top": 676062,
            "position": 138612492
        },
        {
            "id": 89,
            "top": 676062,
            "position": 117297232
        },
        {
            "id": 90,
            "top": 676062,
            "position": 149498605
        },
        {
            "id": 91,
            "top": 676062,
            "position": 238649886
        },
        {
            "id": 92,
            "top": 676062,
            "position": 156170322
        },
        {
            "id": 93,
            "top": 676062,
            "position": 81554997
        },
        {
            "id": 94,
            "top": 676062,
            "position": 140894706
        },
        {
            "id": 95,
            "top": 676062,
            "position": 134742096
        },
        {
            "id": 96,
            "top": 676062,
            "position": 126706773
        },
        {
            "id": 97,
            "top": 676062,
            "position": 52732836
        },
        {
            "id": 98,
            "top": 676062,
            "position": 39281017
        },
        {
            "id": 99,
            "top": 676062,
            "position": 132694383
        },
        {
            "id": 100,
            "top": 676062,
            "position": 90592662
        },
        {
            "id": 101,
            "top": 676062,
            "position": 21633984
        },
        {
            "id": 102,
            "top": 676062,
            "position": 136528624
        },
        {
            "id": 103,
            "top": 676062,
            "position": 207121410
        },
        {
            "id": 104,
            "top": 676062,
            "position": 92167364
        },
        {
            "id": 105,
            "top": 676062,
            "position": 139295326
        },
        {
            "id": 106,
            "top": 676062,
            "position": 155136990
        },
        {
            "id": 107,
            "top": 676062,
            "position": 130229191
        },
        {
            "id": 108,
            "top": 676062,
            "position": 141598756
        },
        {
            "id": 109,
            "top": 676062,
            "position": 136564524
        },
        {
            "id": 110,
            "top": 676062,
            "position": 88398511
        },
        {
            "id": 111,
            "top": 676062,
            "position": 63211797
        },
        {
            "id": 112,
            "top": 676062,
            "position": 119929705
        },
        {
            "id": 113,
            "top": 676062,
            "position": 110792006
        },
        {
            "id": 114,
            "top": 676062,
            "position": 69296538
        },
        {
            "id": 115,
            "top": 676062,
            "position": 106480269
        },
        {
            "id": 116,
            "top": 676062,
            "position": 86316153
        },
        {
            "id": 117,
            "top": 676062,
            "position": 83063551
        },
        {
            "id": 118,
            "top": 676062,
            "position": 141500980
        },
        {
            "id": 119,
            "top": 676062,
            "position": 100558446
        },
        {
            "id": 120,
            "top": 676062,
            "position": 163716510
        },
        {
            "id": 121,
            "top": 676062,
            "position": 63549997
        },
        {
            "id": 122,
            "top": 676062,
            "position": 112722065
        },
        {
            "id": 123,
            "top": 676062,
            "position": 155223598
        },
        {
            "id": 124,
            "top": 676062,
            "position": 77747130
        },
        {
            "id": 125,
            "top": 676062,
            "position": 122802327
        },
        {
            "id": 126,
            "top": 676062,
            "position": 53085204
        },
        {
            "id": 127,
            "top": 676062,
            "position": 59493456
        },
        {
            "id": 128,
            "top": 676062,
            "position": 46648278
        },
        {
            "id": 129,
            "top": 676062,
            "position": 104725060
        },
        {
            "id": 130,
            "top": 676062,
            "position": 123525975
        },
        {
            "id": 131,
            "top": 676062,
            "position": 168339438
        },
        {
            "id": 132,
            "top": 676062,
            "position": 75042882
        },
        {
            "id": 133,
            "top": 676062,
            "position": 152790012
        },
        {
            "id": 134,
            "top": 676062,
            "position": 130923215
        },
        {
            "id": 135,
            "top": 676062,
            "position": 76395006
        },
        {
            "id": 136,
            "top": 676062,
            "position": 125361506
        },
        {
            "id": 137,
            "top": 676062,
            "position": 210931344
        },
        {
            "id": 138,
            "top": 676062,
            "position": 115922076
        },
        {
            "id": 139,
            "top": 676062,
            "position": 83832798
        },
        {
            "id": 140,
            "top": 676062,
            "position": 141564944
        },
        {
            "id": 141,
            "top": 676062,
            "position": 72929566
        },
        {
            "id": 142,
            "top": 676062,
            "position": 32788969
        },
        {
            "id": 143,
            "top": 676062,
            "position": 135140707
        },
        {
            "id": 144,
            "top": 676062,
            "position": 126631816
        },
        {
            "id": 145,
            "top": 676062,
            "position": 48000402
        },
        {
            "id": 146,
            "top": 676062,
            "position": 136827441
        },
        {
            "id": 147,
            "top": 676062,
            "position": 100057176
        },
        {
            "id": 148,
            "top": 676062,
            "position": 144149442
        },
        {
            "id": 149,
            "top": 676062,
            "position": 128068978
        },
        {
            "id": 150,
            "top": 676062,
            "position": 108565447
        },
        {
            "id": 151,
            "top": 676062,
            "position": 169691562
        },
        {
            "id": 152,
            "top": 676062,
            "position": 130386162
        },
        {
            "id": 153,
            "top": 676062,
            "position": 51042684
        },
        {
            "id": 154,
            "top": 676062,
            "position": 76056411
        },
        {
            "id": 155,
            "top": 676062,
            "position": 165223644
        },
        {
            "id": 156,
            "top": 676062,
            "position": 143249902
        },
        {
            "id": 157,
            "top": 676062,
            "position": 139075403
        },
        {
            "id": 158,
            "top": 676062,
            "position": 13521240
        },
        {
            "id": 159,
            "top": 676062,
            "position": 97429439
        },
        {
            "id": 160,
            "top": 676062,
            "position": 125017563
        },
        {
            "id": 161,
            "top": 676062,
            "position": 64563750
        },
        {
            "id": 162,
            "top": 676062,
            "position": 128557803
        },
        {
            "id": 163,
            "top": 676062,
            "position": 149409702
        },
        {
            "id": 164,
            "top": 676062,
            "position": 132509713
        },
        {
            "id": 165,
            "top": 676062,
            "position": 14873343
        },
        {
            "id": 166,
            "top": 676062,
            "position": 216314910
        },
        {
            "id": 167,
            "top": 676062,
            "position": 124089673
        },
        {
            "id": 168,
            "top": 676062,
            "position": 93686963
        },
        {
            "id": 169,
            "top": 676062,
            "position": 151538008
        },
        {
            "id": 170,
            "top": 676062,
            "position": 130146117
        },
        {
            "id": 171,
            "top": 676062,
            "position": 170842078
        },
        {
            "id": 172,
            "top": 676062,
            "position": 72003177
        },
        {
            "id": 173,
            "top": 676062,
            "position": 102085084
        },
        {
            "id": 174,
            "top": 676062,
            "position": 95231232
        },
        {
            "id": 175,
            "top": 676062,
            "position": 131832900
        },
        {
            "id": 176,
            "top": 676062,
            "position": 140142367
        },
        {
            "id": 177,
            "top": 676062,
            "position": 69839640
        },
        {
            "id": 178,
            "top": 676062,
            "position": 127550291
        },
        {
            "id": 179,
            "top": 676062,
            "position": 139419310
        },
        {
            "id": 180,
            "top": 676062,
            "position": 147071481
        },
        {
            "id": 181,
            "top": 676062,
            "position": 135309144
        },
        {
            "id": 182,
            "top": 676062,
            "position": 118804363
        },
        {
            "id": 183,
            "top": 676062,
            "position": 122025110
        },
        {
            "id": 184,
            "top": 676062,
            "position": 91944432
        },
        {
            "id": 185,
            "top": 676062,
            "position": 92745190
        },
        {
            "id": 186,
            "top": 676062,
            "position": 189297360
        },
        {
            "id": 187,
            "top": 676062,
            "position": 187269174
        },
        {
            "id": 188,
            "top": 676062,
            "position": 60168906
        },
        {
            "id": 189,
            "top": 676062,
            "position": 234593514
        },
        {
            "id": 190,
            "top": 676062,
            "position": 99382514
        },
        {
            "id": 191,
            "top": 676062,
            "position": 23662225
        },
        {
            "id": 192,
            "top": 676062,
            "position": 113143997
        },
        {
            "id": 193,
            "top": 676062,
            "position": 140314310
        },
        {
            "id": 194,
            "top": 676062,
            "position": 108694791
        },
        {
            "id": 195,
            "top": 676062,
            "position": 68561700
        },
        {
            "id": 196,
            "top": 676062,
            "position": 139509911
        },
        {
            "id": 197,
            "top": 676062,
            "position": 131156640
        },
        {
            "id": 198,
            "top": 676062,
            "position": 79437690
        },
        {
            "id": 199,
            "top": 676062,
            "position": 250819002
        },
        {
            "id": 200,
            "top": 676062,
            "position": 114604221
        },
        {
            "id": 201,
            "top": 676062,
            "position": 106701378
        },
        {
            "id": 202,
            "top": 676062,
            "position": 44620092
        },
        {
            "id": 203,
            "top": 676062,
            "position": 209244614
        },
        {
            "id": 204,
            "top": 676062,
            "position": 135174234
        },
        {
            "id": 205,
            "top": 676062,
            "position": 78641809
        },
        {
            "id": 206,
            "top": 676062,
            "position": 72338928
        },
        {
            "id": 207,
            "top": 676062,
            "position": 82479804
        },
        {
            "id": 208,
            "top": 676062,
            "position": 104207640
        },
        {
            "id": 209,
            "top": 676062,
            "position": 134346683
        },
        {
            "id": 210,
            "top": 676062,
            "position": 193063188
        },
        {
            "id": 211,
            "top": 676062,
            "position": 103464836
        },
        {
            "id": 212,
            "top": 676062,
            "position": 100733238
        },
        {
            "id": 213,
            "top": 676062,
            "position": 68282100
        },
        {
            "id": 214,
            "top": 676062,
            "position": 125087357
        },
        {
            "id": 215,
            "top": 676062,
            "position": 87211998
        },
        {
            "id": 216,
            "top": 676062,
            "position": 31436841
        },
        {
            "id": 217,
            "top": 676062,
            "position": 79297383
        },
        {
            "id": 218,
            "top": 676062,
            "position": 102085362
        },
        {
            "id": 219,
            "top": 676062,
            "position": 114592210
        },
        {
            "id": 220,
            "top": 676062,
            "position": 177708375
        },
        {
            "id": 221,
            "top": 676062,
            "position": 50294112
        },
        {
            "id": 222,
            "top": 676062,
            "position": 129840388
        },
        {
            "id": 223,
            "top": 676062,
            "position": 92620246
        },
        {
            "id": 224,
            "top": 676062,
            "position": 136145556
        },
        {
            "id": 225,
            "top": 676062,
            "position": 145082557
        },
        {
            "id": 226,
            "top": 676062,
            "position": 96001234
        },
        {
            "id": 227,
            "top": 676062,
            "position": 35493338
        },
        {
            "id": 228,
            "top": 676062,
            "position": 140395567
        },
        {
            "id": 229,
            "top": 676062,
            "position": 127268255
        },
        {
            "id": 230,
            "top": 676062,
            "position": 94309317
        },
        {
            "id": 231,
            "top": 676062,
            "position": 99932108
        },
        {
            "id": 232,
            "top": 676062,
            "position": 154891520
        },
        {
            "id": 233,
            "top": 676062,
            "position": 131126333
        },
        {
            "id": 234,
            "top": 676062,
            "position": 200790414
        },
        {
            "id": 235,
            "top": 676062,
            "position": 131589701
        },
        {
            "id": 236,
            "top": 676062,
            "position": 65239853
        },
        {
            "id": 237,
            "top": 676062,
            "position": 12845178
        },
        {
            "id": 238,
            "top": 676062,
            "position": 76733433
        },
        {
            "id": 239,
            "top": 676062,
            "position": 140835139
        },
        {
            "id": 240,
            "top": 676062,
            "position": 183212802
        },
        {
            "id": 241,
            "top": 676062,
            "position": 165601436
        },
        {
            "id": 242,
            "top": 676062,
            "position": 111396230
        },
        {
            "id": 243,
            "top": 676062,
            "position": 59831646
        },
        {
            "id": 244,
            "top": 676062,
            "position": 105465672
        },
        {
            "id": 245,
            "top": 676062,
            "position": 82874328
        },
        {
            "id": 246,
            "top": 676062,
            "position": 144082133
        },
        {
            "id": 247,
            "top": 676062,
            "position": 131210770
        },
        {
            "id": 248,
            "top": 676062,
            "position": 98705052
        },
        {
            "id": 249,
            "top": 676062,
            "position": 121353633
        },
        {
            "id": 250,
            "top": 676062,
            "position": 181184616
        },
        {
            "id": 251,
            "top": 676062,
            "position": 130461591
        },
        {
            "id": 252,
            "top": 676062,
            "position": 254875374
        },
        {
            "id": 253,
            "top": 676062,
            "position": 173905998
        },
        {
            "id": 254,
            "top": 676062,
            "position": 164283066
        },
        {
            "id": 255,
            "top": 676062,
            "position": 42381360
        },
        {
            "id": 256,
            "top": 676062,
            "position": 137604163
        },
        {
            "id": 257,
            "top": 676062,
            "position": 119855004
        },
        {
            "id": 258,
            "top": 676062,
            "position": 127229371
        },
        {
            "id": 259,
            "top": 676062,
            "position": 83813157
        },
        {
            "id": 260,
            "top": 676062,
            "position": 110198106
        },
        {
            "id": 261,
            "top": 676062,
            "position": 161459879
        },
        {
            "id": 262,
            "top": 676062,
            "position": 162254880
        },
        {
            "id": 263,
            "top": 676062,
            "position": 56451942
        },
        {
            "id": 264,
            "top": 676062,
            "position": 89240184
        },
        {
            "id": 265,
            "top": 676062,
            "position": 155258771
        },
        {
            "id": 266,
            "top": 676062,
            "position": 61010125
        },
        {
            "id": 267,
            "top": 676062,
            "position": 141405232
        },
        {
            "id": 268,
            "top": 676062,
            "position": 123653775
        },
        {
            "id": 269,
            "top": 676062,
            "position": 36507348
        },
        {
            "id": 270,
            "top": 676062,
            "position": 156689461
        },
        {
            "id": 271,
            "top": 676062,
            "position": 148733640
        },
        {
            "id": 272,
            "top": 676062,
            "position": 175100058
        },
        {
            "id": 273,
            "top": 676062,
            "position": 145225211
        },
        {
            "id": 274,
            "top": 676062,
            "position": 72000603
        },
        {
            "id": 275,
            "top": 676062,
            "position": 49014495
        },
        {
            "id": 276,
            "top": 676062,
            "position": 225804708
        },
        {
            "id": 277,
            "top": 676062,
            "position": 125071470
        },
        {
            "id": 278,
            "top": 676062,
            "position": 56616966
        },
        {
            "id": 279,
            "top": 676062,
            "position": 84508590
        },
        {
            "id": 280,
            "top": 676062,
            "position": 52732869
        },
        {
            "id": 281,
            "top": 676062,
            "position": 48676586
        },
        {
            "id": 282,
            "top": 676062,
            "position": 72990435
        },
        {
            "id": 283,
            "top": 676062,
            "position": 253523250
        },
        {
            "id": 284,
            "top": 676062,
            "position": 159430739
        },
        {
            "id": 285,
            "top": 676062,
            "position": 88248118
        },
        {
            "id": 286,
            "top": 676062,
            "position": 117977211
        },
        {
            "id": 287,
            "top": 676062,
            "position": 50028712
        },
        {
            "id": 288,
            "top": 676062,
            "position": 58141478
        },
        {
            "id": 289,
            "top": 676062,
            "position": 44620218
        },
        {
            "id": 290,
            "top": 676062,
            "position": 131629306
        },
        {
            "id": 291,
            "top": 676062,
            "position": 68282552
        },
        {
            "id": 292,
            "top": 676062,
            "position": 20281860
        },
        {
            "id": 293,
            "top": 676062,
            "position": 132898710
        },
        {
            "id": 294,
            "top": 676062,
            "position": 133864609
        },
        {
            "id": 295,
            "top": 676062,
            "position": 18253674
        },
        {
            "id": 296,
            "top": 676062,
            "position": 87304593
        },
        {
            "id": 297,
            "top": 676062,
            "position": 78425194
        },
        {
            "id": 298,
            "top": 676062,
            "position": 129691227
        },
        {
            "id": 299,
            "top": 676062,
            "position": 88902387
        },
        {
            "id": 300,
            "top": 676062,
            "position": 60117959
        },
        {
            "id": 301,
            "top": 676062,
            "position": 133623311
        },
        {
            "id": 302,
            "top": 676062,
            "position": 83108273
        },
        {
            "id": 303,
            "top": 676062,
            "position": 94003475
        },
        {
            "id": 304,
            "top": 676062,
            "position": 160226694
        },
        {
            "id": 305,
            "top": 676062,
            "position": 79772923
        },
        {
            "id": 306,
            "top": 676062,
            "position": 16225526
        },
        {
            "id": 307,
            "top": 676062,
            "position": 123214034
        },
        {
            "id": 308,
            "top": 676062,
            "position": 258931746
        },
        {
            "id": 309,
            "top": 676062,
            "position": 177128244
        },
        {
            "id": 310,
            "top": 676062,
            "position": 142649082
        },
        {
            "id": 311,
            "top": 676062,
            "position": 110947399
        },
        {
            "id": 312,
            "top": 676062,
            "position": 47661732
        },
        {
            "id": 313,
            "top": 676062,
            "position": 57127109
        },
        {
            "id": 314,
            "top": 676062,
            "position": 122687805
        },
        {
            "id": 315,
            "top": 676062,
            "position": 63488361
        },
        {
            "id": 316,
            "top": 676062,
            "position": 90792670
        },
        {
            "id": 317,
            "top": 676062,
            "position": 130763023
        },
        {
            "id": 318,
            "top": 676062,
            "position": 154268502
        },
        {
            "id": 319,
            "top": 676062,
            "position": 70108971
        },
        {
            "id": 320,
            "top": 676062,
            "position": 235945638
        },
        {
            "id": 321,
            "top": 676062,
            "position": 64564084
        },
        {
            "id": 322,
            "top": 676062,
            "position": 134848317
        },
        {
            "id": 323,
            "top": 676062,
            "position": 245410506
        },
        {
            "id": 324,
            "top": 676062,
            "position": 119865706
        },
        {
            "id": 325,
            "top": 676062,
            "position": 55535825
        },
        {
            "id": 326,
            "top": 676062,
            "position": 28394545
        },
        {
            "id": 327,
            "top": 676062,
            "position": 157396461
        },
        {
            "id": 328,
            "top": 676062,
            "position": 120704888
        },
        {
            "id": 329,
            "top": 676062,
            "position": 136183124
        },
        {
            "id": 330,
            "top": 676062,
            "position": 124080641
        },
        {
            "id": 331,
            "top": 676062,
            "position": 149279584
        },
        {
            "id": 332,
            "top": 676062,
            "position": 71744890
        },
        {
            "id": 333,
            "top": 676062,
            "position": 171043686
        },
        {
            "id": 334,
            "top": 676062,
            "position": 104113548
        },
        {
            "id": 335,
            "top": 676062,
            "position": 30422750
        },
        {
            "id": 336,
            "top": 676062,
            "position": 187945236
        },
        {
            "id": 337,
            "top": 676062,
            "position": 141091432
        },
        {
            "id": 338,
            "top": 676062,
            "position": 61276874
        },
        {
            "id": 339,
            "top": 676062,
            "position": 91606644
        },
        {
            "id": 340,
            "top": 676062,
            "position": 148210553
        },
        {
            "id": 341,
            "top": 676062,
            "position": 20958174
        },
        {
            "id": 342,
            "top": 676062,
            "position": 87212388
        },
        {
            "id": 343,
            "top": 676062,
            "position": 113665475
        },
        {
            "id": 344,
            "top": 676062,
            "position": 45018945
        },
        {
            "id": 345,
            "top": 676062,
            "position": 128071914
        },
        {
            "id": 346,
            "top": 676062,
            "position": 126423755
        },
        {
            "id": 347,
            "top": 676062,
            "position": 76945350
        },
        {
            "id": 348,
            "top": 676062,
            "position": 123972638
        },
        {
            "id": 349,
            "top": 676062,
            "position": 6084558
        },
        {
            "id": 350,
            "top": 676062,
            "position": 144152940
        },
        {
            "id": 351,
            "top": 676062,
            "position": 116582186
        },
        {
            "id": 352,
            "top": 676062,
            "position": 134787142
        },
        {
            "id": 353,
            "top": 676062,
            "position": 62197563
        },
        {
            "id": 354,
            "top": 676062,
            "position": 106950384
        },
        {
            "id": 355,
            "top": 676062,
            "position": 130562669
        },
        {
            "id": 356,
            "top": 676062,
            "position": 146640475
        },
        {
            "id": 357,
            "top": 676062,
            "position": 101913527
        },
        {
            "id": 358,
            "top": 676062,
            "position": 80927734
        },
        {
            "id": 359,
            "top": 676062,
            "position": 56113494
        },
        {
            "id": 360,
            "top": 676062,
            "position": 31257426
        },
        {
            "id": 361,
            "top": 676062,
            "position": 128451780
        },
        {
            "id": 362,
            "top": 676062,
            "position": 130550936
        },
        {
            "id": 363,
            "top": 676062,
            "position": 91406181
        },
        {
            "id": 364,
            "top": 676062,
            "position": 226480770
        },
        {
            "id": 365,
            "top": 676062,
            "position": 145240736
        },
        {
            "id": 366,
            "top": 676062,
            "position": 74367018
        },
        {
            "id": 367,
            "top": 676062,
            "position": 11493054
        },
        {
            "id": 368,
            "top": 676062,
            "position": 177128244
        },
        {
            "id": 369,
            "top": 676062,
            "position": 65910330
        },
        {
            "id": 370,
            "top": 676062,
            "position": 100395045
        },
        {
            "id": 371,
            "top": 676062,
            "position": 206874972
        },
        {
            "id": 372,
            "top": 676062,
            "position": 145353174
        },
        {
            "id": 373,
            "top": 676062,
            "position": 84627554
        },
        {
            "id": 374,
            "top": 676062,
            "position": 88444297
        },
        {
            "id": 375,
            "top": 676062,
            "position": 116957925
        },
        {
            "id": 376,
            "top": 676062,
            "position": 92958774
        },
        {
            "id": 377,
            "top": 676062,
            "position": 150473491
        },
        {
            "id": 378,
            "top": 676062,
            "position": 146387064
        },
        {
            "id": 379,
            "top": 676062,
            "position": 201503768
        },
        {
            "id": 380,
            "top": 676062,
            "position": 73259569
        },
        {
            "id": 381,
            "top": 676062,
            "position": 129127842
        },
        {
            "id": 382,
            "top": 676062,
            "position": 67606385
        },
        {
            "id": 383,
            "top": 676062,
            "position": 168596552
        },
        {
            "id": 384,
            "top": 676062,
            "position": 51380574
        },
        {
            "id": 385,
            "top": 676062,
            "position": 72676521
        },
        {
            "id": 386,
            "top": 676062,
            "position": 81195439
        },
        {
            "id": 387,
            "top": 676062,
            "position": 98565205
        },
        {
            "id": 388,
            "top": 676062,
            "position": 142356500
        },
        {
            "id": 389,
            "top": 676062,
            "position": 242030196
        },
        {
            "id": 390,
            "top": 676062,
            "position": 195381918
        },
        {
            "id": 391,
            "top": 676062,
            "position": 139700522
        },
        {
            "id": 392,
            "top": 676062,
            "position": 85235460
        },
        {
            "id": 393,
            "top": 676062,
            "position": 160077438
        },
        {
            "id": 394,
            "top": 676062,
            "position": 270424800
        },
        {
            "id": 395,
            "top": 676062,
            "position": 165089359
        },
        {
            "id": 396,
            "top": 676062,
            "position": 144677268
        },
        {
            "id": 397,
            "top": 676062,
            "position": 132785758
        },
        {
            "id": 398,
            "top": 676062,
            "position": 103714413
        },
        {
            "id": 399,
            "top": 676062,
            "position": 99042030
        },
        {
            "id": 400,
            "top": 676062,
            "position": 136718518
        },
        {
            "id": 401,
            "top": 676062,
            "position": 98634537
        },
        {
            "id": 402,
            "top": 676062,
            "position": 138592568
        },
        {
            "id": 403,
            "top": 676062,
            "position": 55767057
        },
        {
            "id": 404,
            "top": 676062,
            "position": 140784831
        },
        {
            "id": 405,
            "top": 676062,
            "position": 77733828
        },
        {
            "id": 406,
            "top": 676062,
            "position": 89398633
        },
        {
            "id": 407,
            "top": 676062,
            "position": 78085370
        },
        {
            "id": 408,
            "top": 676062,
            "position": 157313233
        },
        {
            "id": 409,
            "top": 676062,
            "position": 131384333
        },
        {
            "id": 410,
            "top": 676062,
            "position": 131440172
        },
        {
            "id": 411,
            "top": 676062,
            "position": 139401695
        },
        {
            "id": 412,
            "top": 676062,
            "position": 117518945
        },
        {
            "id": 413,
            "top": 676062,
            "position": 30084733
        },
        {
            "id": 414,
            "top": 676062,
            "position": 93972973
        },
        {
            "id": 415,
            "top": 676062,
            "position": 125851456
        },
        {
            "id": 416,
            "top": 676062,
            "position": 77409389
        },
        {
            "id": 417,
            "top": 676062,
            "position": 14873364
        },
        {
            "id": 418,
            "top": 676062,
            "position": 111177126
        },
        {
            "id": 419,
            "top": 676062,
            "position": 130902423
        },
        {
            "id": 420,
            "top": 676062,
            "position": 113917158
        },
        {
            "id": 421,
            "top": 676062,
            "position": 194216779
        },
        {
            "id": 422,
            "top": 676062,
            "position": 66253940
        },
        {
            "id": 423,
            "top": 676062,
            "position": 50028489
        },
        {
            "id": 424,
            "top": 676062,
            "position": 45296275
        },
        {
            "id": 425,
            "top": 676062,
            "position": 85182948
        },
        {
            "id": 426,
            "top": 676062,
            "position": 113032952
        },
        {
            "id": 427,
            "top": 676062,
            "position": 177736352
        },
        {
            "id": 428,
            "top": 676062,
            "position": 123043584
        },
        {
            "id": 429,
            "top": 676062,
            "position": 109889280
        },
        {
            "id": 430,
            "top": 676062,
            "position": 144287118
        },
        {
            "id": 431,
            "top": 676062,
            "position": 135505514
        },
        {
            "id": 432,
            "top": 676062,
            "position": 87887601
        },
        {
            "id": 433,
            "top": 676062,
            "position": 119695893
        },
        {
            "id": 434,
            "top": 676062,
            "position": 143700734
        },
        {
            "id": 435,
            "top": 676062,
            "position": 80789623
        },
        {
            "id": 436,
            "top": 676062,
            "position": 233241390
        },
        {
            "id": 437,
            "top": 676062,
            "position": 106606526
        },
        {
            "id": 438,
            "top": 676062,
            "position": 145472302
        },
        {
            "id": 439,
            "top": 676062,
            "position": 91524538
        },
        {
            "id": 440,
            "top": 676062,
            "position": 83455944
        },
        {
            "id": 441,
            "top": 676062,
            "position": 174536673
        },
        {
            "id": 442,
            "top": 676062,
            "position": 85522069
        },
        {
            "id": 443,
            "top": 676062,
            "position": 82482060
        },
        {
            "id": 444,
            "top": 676062,
            "position": 116282664
        },
        {
            "id": 445,
            "top": 676062,
            "position": 108482533
        },
        {
            "id": 446,
            "top": 676062,
            "position": 84507750
        },
        {
            "id": 447,
            "top": 676062,
            "position": 157390173
        },
        {
            "id": 448,
            "top": 676062,
            "position": 93642190
        },
        {
            "id": 449,
            "top": 676062,
            "position": 67606200
        },
        {
            "id": 450,
            "top": 676062,
            "position": 82432692
        },
        {
            "id": 451,
            "top": 676062,
            "position": 130179494
        },
        {
            "id": 452,
            "top": 676062,
            "position": 42930052
        },
        {
            "id": 453,
            "top": 676062,
            "position": 39887658
        },
        {
            "id": 454,
            "top": 676062,
            "position": 115637557
        },
        {
            "id": 455,
            "top": 676062,
            "position": 93297009
        },
        {
            "id": 456,
            "top": 676062,
            "position": 227832894
        },
        {
            "id": 457,
            "top": 676062,
            "position": 117356615
        },
        {
            "id": 458,
            "top": 676062,
            "position": 148353388
        },
        {
            "id": 459,
            "top": 676062,
            "position": 140513121
        },
        {
            "id": 460,
            "top": 676062,
            "position": 117635268
        },
        {
            "id": 461,
            "top": 676062,
            "position": 123044211
        },
        {
            "id": 462,
            "top": 676062,
            "position": 146082565
        },
        {
            "id": 463,
            "top": 676062,
            "position": 119591415
        },
        {
            "id": 464,
            "top": 676062,
            "position": 131247816
        },
        {
            "id": 465,
            "top": 676062,
            "position": 85774150
        },
        {
            "id": 466,
            "top": 676062,
            "position": 151437888
        },
        {
            "id": 467,
            "top": 676062,
            "position": 136107547
        },
        {
            "id": 468,
            "top": 676062,
            "position": 166105770
        },
        {
            "id": 469,
            "top": 676062,
            "position": 53409162
        },
        {
            "id": 470,
            "top": 676062,
            "position": 93634835
        },
        {
            "id": 471,
            "top": 676062,
            "position": 44619126
        },
        {
            "id": 472,
            "top": 676062,
            "position": 113883510
        },
        {
            "id": 473,
            "top": 676062,
            "position": 97961392
        },
        {
            "id": 474,
            "top": 676062,
            "position": 100395477
        },
        {
            "id": 475,
            "top": 676062,
            "position": 98937167
        },
        {
            "id": 476,
            "top": 676062,
            "position": 127775718
        },
        {
            "id": 477,
            "top": 676062,
            "position": 182536740
        },
        {
            "id": 478,
            "top": 676062,
            "position": 48000521
        },
        {
            "id": 479,
            "top": 676062,
            "position": 41915956
        },
        {
            "id": 480,
            "top": 676062,
            "position": 128175642
        },
        {
            "id": 481,
            "top": 676062,
            "position": 62197704
        },
        {
            "id": 482,
            "top": 676062,
            "position": 142292404
        },
        {
            "id": 483,
            "top": 676062,
            "position": 109722807
        },
        {
            "id": 484,
            "top": 676062,
            "position": 17239620
        },
        {
            "id": 485,
            "top": 676062,
            "position": 144331075
        },
        {
            "id": 486,
            "top": 676062,
            "position": 192677670
        },
        {
            "id": 487,
            "top": 676062,
            "position": 74028631
        },
        {
            "id": 488,
            "top": 676062,
            "position": 75020626
        },
        {
            "id": 489,
            "top": 676062,
            "position": 106093171
        },
        {
            "id": 490,
            "top": 676062,
            "position": 139393919
        },
        {
            "id": 491,
            "top": 676062,
            "position": 79775316
        },
        {
            "id": 492,
            "top": 676062,
            "position": 137678482
        },
        {
            "id": 493,
            "top": 676062,
            "position": 256227498
        },
        {
            "id": 494,
            "top": 676062,
            "position": 154265192
        },
        {
            "id": 495,
            "top": 676062,
            "position": 104789610
        },
        {
            "id": 496,
            "top": 676062,
            "position": 124121423
        },
        {
            "id": 497,
            "top": 676062,
            "position": 128346332
        },
        {
            "id": 498,
            "top": 676062,
            "position": 196071228
        },
        {
            "id": 499,
            "top": 676062,
            "position": 141790481
        }
    ],
    "qualite": 0.3719683251809238,
    "temperature": -6.311407133554969
}