{
    "tortoises": [
        {
            "id": 0,
            "top": 673853,
            "position": 56603652
        },
        {
            "id": 1,
            "top": 673853,
            "position": 106806219
        },
        {
            "id": 2,
            "top": 673853,
            "position": 260107258
        },
        {
            "id": 3,
            "top": 673853,
            "position": 144012118
        },
        {
            "id": 4,
            "top": 673853,
            "position": 147652994
        },
        {
            "id": 5,
            "top": 673853,
            "position": 132530718
        },
        {
            "id": 6,
            "top": 673853,
            "position": 214959107
        },
        {
            "id": 7,
            "top": 673853,
            "position": 115566477
        },
        {
            "id": 8,
            "top": 673853,
            "position": 103099509
        },
        {
            "id": 9,
            "top": 673853,
            "position": 128245135
        }
    ],
    "qualite": 0.3100529516794682,
    "temperature": 40.0
}