{
    "tortoises": [
        {
            "id": 0,
            "top": 675265,
            "position": 66851235
        },
        {
            "id": 1,
            "top": 675265,
            "position": 129522417
        },
        {
            "id": 2,
            "top": 675265,
            "position": 37659736
        },
        {
            "id": 3,
            "top": 675265,
            "position": 150346694
        },
        {
            "id": 4,
            "top": 675265,
            "position": 127372561
        },
        {
            "id": 5,
            "top": 675265,
            "position": 132312812
        },
        {
            "id": 6,
            "top": 675265,
            "position": 174511896
        },
        {
            "id": 7,
            "top": 675265,
            "position": 118154244
        },
        {
            "id": 8,
            "top": 675265,
            "position": 155349782
        },
        {
            "id": 9,
            "top": 675265,
            "position": 78598872
        },
        {
            "id": 10,
            "top": 675265,
            "position": 87376531
        },
        {
            "id": 11,
            "top": 675265,
            "position": 116148587
        },
        {
            "id": 12,
            "top": 675265,
            "position": 186009398
        },
        {
            "id": 13,
            "top": 675265,
            "position": 238537523
        },
        {
            "id": 14,
            "top": 675265,
            "position": 120197170
        },
        {
            "id": 15,
            "top": 675265,
            "position": 113781568
        },
        {
            "id": 16,
            "top": 675265,
            "position": 191099995
        },
        {
            "id": 17,
            "top": 675265,
            "position": 109056355
        },
        {
            "id": 18,
            "top": 675265,
            "position": 224187980
        },
        {
            "id": 19,
            "top": 675265,
            "position": 242462200
        },
        {
            "id": 20,
            "top": 675265,
            "position": 209332150
        },
        {
            "id": 21,
            "top": 675265,
            "position": 84408125
        },
        {
            "id": 22,
            "top": 675265,
            "position": 88122455
        },
        {
            "id": 23,
            "top": 675265,
            "position": 168816250
        },
        {
            "id": 24,
            "top": 675265,
            "position": 113326153
        },
        {
            "id": 25,
            "top": 675265,
            "position": 136479594
        },
        {
            "id": 26,
            "top": 675265,
            "position": 136140759
        },
        {
            "id": 27,
            "top": 675265,
            "position": 62799834
        },
        {
            "id": 28,
            "top": 675265,
            "position": 12830035
        },
        {
            "id": 29,
            "top": 675265,
            "position": 140149183
        },
        {
            "id": 30,
            "top": 675265,
            "position": 10128975
        },
        {
            "id": 31,
            "top": 675265,
            "position": 134830498
        },
        {
            "id": 32,
            "top": 675265,
            "position": 147115852
        },
        {
            "id": 33,
            "top": 675265,
            "position": 35186998
        },
        {
            "id": 34,
            "top": 675265,
            "position": 167482477
        },
        {
            "id": 35,
            "top": 675265,
            "position": 142051250
        },
        {
            "id": 36,
            "top": 675265,
            "position": 88797715
        },
        {
            "id": 37,
            "top": 675265,
            "position": 173091148
        },
        {
            "id": 38,
            "top": 675265,
            "position": 142799381
        },
        {
            "id": 39,
            "top": 675265,
            "position": 136480923
        },
        {
            "id": 40,
            "top": 675265,
            "position": 266054410
        },
        {
            "id": 41,
            "top": 675265,
            "position": 74552006
        },
        {
            "id": 42,
            "top": 675265,
            "position": 36464220
        },
        {
            "id": 43,
            "top": 675265,
            "position": 64150270
        },
        {
            "id": 44,
            "top": 675265,
            "position": 120537165
        },
        {
            "id": 45,
            "top": 675265,
            "position": 152872981
        },
        {
            "id": 46,
            "top": 675265,
            "position": 131053254
        },
        {
            "id": 47,
            "top": 675265,
            "position": 39503601
        },
        {
            "id": 48,
            "top": 675265,
            "position": 76113357
        },
        {
            "id": 49,
            "top": 675265,
            "position": 126635030
        },
        {
            "id": 50,
            "top": 675265,
            "position": 96225825
        },
        {
            "id": 51,
            "top": 675265,
            "position": 138247291
        },
        {
            "id": 52,
            "top": 675265,
            "position": 151647801
        },
        {
            "id": 53,
            "top": 675265,
            "position": 124356510
        },
        {
            "id": 54,
            "top": 675265,
            "position": 130678728
        },
        {
            "id": 55,
            "top": 675265,
            "position": 184277968
        },
        {
            "id": 56,
            "top": 675265,
            "position": 161728648
        },
        {
            "id": 57,
            "top": 675265,
            "position": 64269064
        },
        {
            "id": 58,
            "top": 675265,
            "position": 94537100
        },
        {
            "id": 59,
            "top": 675265,
            "position": 52670670
        },
        {
            "id": 60,
            "top": 675265,
            "position": 151120635
        },
        {
            "id": 61,
            "top": 675265,
            "position": 32075115
        },
        {
            "id": 62,
            "top": 675265,
            "position": 122852712
        },
        {
            "id": 63,
            "top": 675265,
            "position": 133035075
        },
        {
            "id": 64,
            "top": 675265,
            "position": 47606253
        },
        {
            "id": 65,
            "top": 675265,
            "position": 95637740
        },
        {
            "id": 66,
            "top": 675265,
            "position": 228914835
        },
        {
            "id": 67,
            "top": 675265,
            "position": 61250423
        },
        {
            "id": 68,
            "top": 675265,
            "position": 87608637
        },
        {
            "id": 69,
            "top": 675265,
            "position": 110977434
        },
        {
            "id": 70,
            "top": 675265,
            "position": 144871122
        },
        {
            "id": 71,
            "top": 675265,
            "position": 138870618
        },
        {
            "id": 72,
            "top": 675265,
            "position": 107315403
        },
        {
            "id": 73,
            "top": 675265,
            "position": 132453844
        },
        {
            "id": 74,
            "top": 675265,
            "position": 79343183
        },
        {
            "id": 75,
            "top": 675265,
            "position": 137619412
        },
        {
            "id": 76,
            "top": 675265,
            "position": 109729995
        },
        {
            "id": 77,
            "top": 675265,
            "position": 156673289
        },
        {
            "id": 78,
            "top": 675265,
            "position": 139058108
        },
        {
            "id": 79,
            "top": 675265,
            "position": 106691870
        },
        {
            "id": 80,
            "top": 675265,
            "position": 89882268
        },
        {
            "id": 81,
            "top": 675265,
            "position": 126274555
        },
        {
            "id": 82,
            "top": 675265,
            "position": 104327955
        },
        {
            "id": 83,
            "top": 675265,
            "position": 114863671
        },
        {
            "id": 84,
            "top": 675265,
            "position": 140351304
        },
        {
            "id": 85,
            "top": 675265,
            "position": 144647822
        },
        {
            "id": 86,
            "top": 675265,
            "position": 51658542
        },
        {
            "id": 87,
            "top": 675265,
            "position": 91497020
        },
        {
            "id": 88,
            "top": 675265,
            "position": 181108051
        },
        {
            "id": 89,
            "top": 675265,
            "position": 59808735
        },
        {
            "id": 90,
            "top": 675265,
            "position": 3713963
        },
        {
            "id": 91,
            "top": 675265,
            "position": 86148485
        },
        {
            "id": 92,
            "top": 675265,
            "position": 75207784
        },
        {
            "id": 93,
            "top": 675265,
            "position": 43892225
        },
        {
            "id": 94,
            "top": 675265,
            "position": 131390593
        },
        {
            "id": 95,
            "top": 675265,
            "position": 203074473
        },
        {
            "id": 96,
            "top": 675265,
            "position": 119070513
        },
        {
            "id": 97,
            "top": 675265,
            "position": 81371809
        },
        {
            "id": 98,
            "top": 675265,
            "position": 150985004
        },
        {
            "id": 99,
            "top": 675265,
            "position": 133834945
        }
    ],
    "qualite": 0.45689562939730055,
    "temperature": -10.0
}